{"stats":{"minecraft:custom":{"minecraft:time_since_rest":6457,"minecraft:interact_with_furnace":2,"minecraft:sprint_one_cm":751682,"minecraft:damage_taken":7349,"minecraft:walk_one_cm":381733,"minecraft:drop":1,"minecraft:minecart_one_cm":9067,"minecraft:fly_one_cm":1488039,"minecraft:swim_one_cm":16079,"minecraft:interact_with_crafting_table":1,"minecraft:target_hit":10,"minecraft:open_barrel":2,"minecraft:open_chest":4,"minecraft:crouch_one_cm":23420,"minecraft:play_time":297620,"minecraft:deaths":40,"minecraft:sneak_time":13818,"minecraft:walk_under_water_one_cm":20918,"minecraft:boat_one_cm":162227,"minecraft:interact_with_lectern":6,"minecraft:aviate_one_cm":73225,"minecraft:jump":2876,"minecraft:time_since_death":6454,"minecraft:leave_game":15,"minecraft:walk_on_water_one_cm":10354,"minecraft:climb_one_cm":41555,"minecraft:total_world_time":297620,"minecraft:damage_resisted":4350,"minecraft:fall_one_cm":171319},"minecraft:used":{"minecraft:birch_fence":9,"minecraft:birch_slab":5,"minecraft:spruce_planks":1,"minecraft:stone":1,"minecraft:raw_gold_block":2,"minecraft:stripped_birch_wood":27,"minecraft:player_head":3,"minecraft:yellow_concrete_powder":1,"minecraft:spyglass":17,"minecraft:hay_block":6,"minecraft:oak_sapling":3,"minecraft:yellow_stained_glass_pane":1,"minecraft:gold_block":9,"minecraft:sponge":1,"minecraft:yellow_carpet":1,"minecraft:ochre_froglight":1,"minecraft:snowball":10,"minecraft:birch_stairs":2,"minecraft:honey_bottle":10},"minecraft:dropped":{"minecraft:honey_bottle":1}},"DataVersion":3120}